{
    "/js/app.js": "/js/app.js?id=de06e68cfaf010bfc055",
    "/js/perfect-scrollbar.jquery.min.js": "/js/perfect-scrollbar.jquery.min.js?id=5ced0ff357c23e39784a",
    "/js/bootstrap-notify.js": "/js/bootstrap-notify.js?id=ac307cbc1bbfc98cbdd2",
    "/js/black-dashboard.min.js": "/js/black-dashboard.min.js?id=3f5708c32bfb2cdf18d4",
    "/js/jquery.min.js": "/js/jquery.min.js?id=d2912f53d0623a5ce8ef",
    "/css/app.css": "/css/app.css?id=7dec8f39ff2f79330bb4",
    "/css/black-dashboard.min.css": "/css/black-dashboard.min.css?id=1fe352145cdb89f263a7",
    "/css/nucleo-icons.css": "/css/nucleo-icons.css?id=583815c3d68f7828ac57"
}
